examples/__init__.py
examples/basic_usage.py
quickly/__init__.py
quickly/core.py
quickly/version.py
tests/__init__.py
tests/test_quickly.py
quickly_plot-0.1.0.dist-info/METADATA
quickly_plot-0.1.0.dist-info/WHEEL
quickly_plot-0.1.0.dist-info/top_level.txt
quickly_plot-0.1.0.dist-info/RECORD
